roughpy/libLibalgebra_lite.so
roughpy/_roughpy.pyi
roughpy/_roughpy.cpython-312-x86_64-linux-gnu.so
roughpy/libRoughPy_Platform.so.0.2.0
roughpy/libRoughPy_Algebra.so.0.2.0
roughpy/tensor_functions.py
roughpy/py.typed
roughpy/__init__.py
roughpy/libRoughPy_Streams.so.0.2.0
roughpy/__init__.pyi
roughpy/libRoughPy_Intervals.so.0.2.0
roughpy/version.py
roughpy/libRoughPy_Scalars.so.0.0.9
roughpy/streams/tick_stream.py
roughpy/streams/__init__.py
roughpy-0.2.0.dist-info/METADATA
roughpy-0.2.0.dist-info/RECORD
roughpy-0.2.0.dist-info/WHEEL
roughpy-0.2.0.dist-info/licenses/LICENSE.txt
